{
    "info": {
        "disclaimer": "Muchos de los chistes a continuación son racistas, sexistas o explícitos. ¡Entrar a su propio riesgo!",
        "formatVersion": 3
    },
    "jokes": [
        {
            "category": "Misc",
            "type": "single",
            "joke": "Una ardilla le pregunta a otra que quiere ser cuando grande, la otra ardilla de responde \"Ardila Lülle\".",
            "flags": {
                "nsfw": true,
                "religious": false,
                "political": true,
                "racist": false,
                "sexist": false
            },
            "id": 0,
            "safe": false
        }
    ]
}